{
      "caseId": "1978-132",
      "docketId": "1978-132-01",
      "caseIssuesId": "1978-132-01-02",
      "voteId": "1978-132-01-02-01",
      "dateDecision": "6/20/1979",
      "decisionType": 1,
      "usCite": "442 U.S. 682",
      "sctCite": "99 S. Ct. 2545",
      "ledCite": "61 L. Ed. 2d 176",
      "lexisCite": "1979 U.S. LEXIS 132",
      "term": 1978,
      "naturalCourt": 1506,
      "chief": "Burger",
      "docket": "77-1511",
      "caseName": "CALIFANO, SECRETARY OF HEALTH, EDUCATION, AND WELFARE v. YAMASAKI et al.",
      "dateArgument": "3/19/1979",
      "dateRearg": NaN,
      "petitioner": 362.0,
      "petitionerState": NaN,
      "respondent": 212.0,
      "respondentState": NaN,
      "jurisdiction": 1.0,
      "adminAction": 62.0,
      "adminActionState": NaN,
      "threeJudgeFdc": 0.0,
      "caseOrigin": 63.0,
      "caseOriginState": NaN,
      "caseSource": 29.0,
      "caseSourceState": NaN,
      "lcDisagreement": 0.0,
      "certReason": 12.0,
      "lcDisposition": 2.0,
      "lcDispositionDirection": 1.0,
      "declarationUncon": 1.0,
      "caseDisposition": 6.0,
      "caseDispositionUnusual": 0.0,
      "partyWinning": 1.0,
      "precedentAlteration": 0.0,
      "voteUnclear": 0.0,
      "issue": 40020.0,
      "issueArea": 4.0,
      "decisionDirection": 2.0,
      "decisionDirectionDissent": 0.0,
      "authorityDecision1": 1.0,
      "authorityDecision2": NaN,
      "lawType": 2.0,
      "lawSupp": 207.0,
      "lawMinor": NaN,
      "majOpinWriter": 100.0,
      "majOpinAssigner": 99.0,
      "splitVote": 1,
      "majVotes": 8,
      "minVotes": 0,
      "cite_id": "usrep442682",
      "outpath": "/Users/jnapolitano/Projects/supreme_court_transcripts/oyez/scdb_nodes/usrep442682.json"
}