{
      "caseId": "1959-035",
      "docketId": "1959-035-02",
      "caseIssuesId": "1959-035-02-01",
      "voteId": "1959-035-02-01-01",
      "dateDecision": "2/23/1960",
      "decisionType": 1,
      "usCite": "361 U.S. 459",
      "sctCite": "80 S. Ct. 489",
      "ledCite": "4 L. Ed. 2d 442",
      "lexisCite": "1960 U.S. LEXIS 1951",
      "term": 1959,
      "naturalCourt": 1406,
      "chief": "Warren",
      "docket": "19",
      "caseName": "UNITED MINE WORKERS OF AMERICA et al. v. BENEDICT COAL CORP.",
      "dateArgument": "10/21/1959",
      "dateRearg": NaN,
      "petitioner": 249.0,
      "petitionerState": NaN,
      "respondent": 132.0,
      "respondentState": NaN,
      "jurisdiction": 1.0,
      "adminAction": NaN,
      "adminActionState": NaN,
      "threeJudgeFdc": 0.0,
      "caseOrigin": 116.0,
      "caseOriginState": NaN,
      "caseSource": 26.0,
      "caseSourceState": NaN,
      "lcDisagreement": 0.0,
      "certReason": 12.0,
      "lcDisposition": 2.0,
      "lcDispositionDirection": 1.0,
      "declarationUncon": 1.0,
      "caseDisposition": 8.0,
      "caseDispositionUnusual": 1.0,
      "partyWinning": 1.0,
      "precedentAlteration": 0.0,
      "voteUnclear": 0.0,
      "issue": 80070.0,
      "issueArea": 8.0,
      "decisionDirection": 2.0,
      "decisionDirectionDissent": 0.0,
      "authorityDecision1": 4.0,
      "authorityDecision2": NaN,
      "lawType": 3.0,
      "lawSupp": 350.0,
      "lawMinor": NaN,
      "majOpinWriter": 92.0,
      "majOpinAssigner": 90.0,
      "splitVote": 1,
      "majVotes": 7,
      "minVotes": 1,
      "cite_id": "usrep361459",
      "outpath": "/Users/jnapolitano/Projects/supreme_court_transcripts/oyez/scdb_nodes/usrep361459.json"
}