{
      "caseId": "1948-001",
      "docketId": "1948-001-01",
      "caseIssuesId": "1948-001-01-06",
      "voteId": "1948-001-01-06-01",
      "dateDecision": "10/21/1948",
      "decisionType": 6,
      "usCite": "335 U.S. 281",
      "sctCite": "69 S. Ct. 1",
      "ledCite": "93 L. Ed. 2d 3",
      "lexisCite": "1948 U.S. LEXIS 1668",
      "term": 1948,
      "naturalCourt": 1301,
      "chief": "Vinson",
      "docket": "348",
      "caseName": "MacDOUGALL ET AL. v. GREEN, GOVERNOR OF ILLINOIS, ET AL.",
      "dateArgument": "10/18/1948",
      "dateRearg": NaN,
      "petitioner": 211.0,
      "petitionerState": NaN,
      "respondent": 211.0,
      "respondentState": NaN,
      "jurisdiction": 2.0,
      "adminAction": 117.0,
      "adminActionState": 17.0,
      "threeJudgeFdc": 1.0,
      "caseOrigin": 66.0,
      "caseOriginState": 17.0,
      "caseSource": 66.0,
      "caseSourceState": 17.0,
      "lcDisagreement": 0.0,
      "certReason": 1.0,
      "lcDisposition": NaN,
      "lcDispositionDirection": 1.0,
      "declarationUncon": 1.0,
      "caseDisposition": 2.0,
      "caseDispositionUnusual": 0.0,
      "partyWinning": 0.0,
      "precedentAlteration": 0.0,
      "voteUnclear": 0.0,
      "issue": 20030.0,
      "issueArea": 2.0,
      "decisionDirection": 1.0,
      "decisionDirectionDissent": 0.0,
      "authorityDecision1": 2.0,
      "authorityDecision2": NaN,
      "lawType": 2.0,
      "lawSupp": 236.0,
      "lawMinor": NaN,
      "majOpinWriter": NaN,
      "majOpinAssigner": NaN,
      "splitVote": 1,
      "majVotes": 6,
      "minVotes": 3,
      "cite_id": "usrep335281",
      "outpath": "/Users/jnapolitano/Projects/supreme_court_transcripts/oyez/scdb_nodes/usrep335281.json"
}