{
      "caseId": "1977-030",
      "docketId": "1977-030-01",
      "caseIssuesId": "1977-030-01-01",
      "voteId": "1977-030-01-01-01",
      "dateDecision": "1/23/1978",
      "decisionType": 1,
      "usCite": "434 U.S. 412",
      "sctCite": "98 S. Ct. 694",
      "ledCite": "54 L. Ed. 2d 648",
      "lexisCite": "1978 U.S. LEXIS 148",
      "term": 1977,
      "naturalCourt": 1506,
      "chief": "Burger",
      "docket": "76-1383",
      "caseName": "CHRISTIANSBURG GARMENT CO. v. EQUAL EMPLOYMENT OPPORTUNITY COMMISSION",
      "dateArgument": "11/28/1977",
      "dateRearg": NaN,
      "petitioner": 151.0,
      "petitionerState": NaN,
      "respondent": 332.0,
      "respondentState": NaN,
      "jurisdiction": 1.0,
      "adminAction": 32.0,
      "adminActionState": NaN,
      "threeJudgeFdc": 0.0,
      "caseOrigin": 127.0,
      "caseOriginState": NaN,
      "caseSource": 24.0,
      "caseSourceState": NaN,
      "lcDisagreement": 1.0,
      "certReason": 10.0,
      "lcDisposition": 2.0,
      "lcDispositionDirection": 1.0,
      "declarationUncon": 1.0,
      "caseDisposition": 2.0,
      "caseDispositionUnusual": 0.0,
      "partyWinning": 0.0,
      "precedentAlteration": 0.0,
      "voteUnclear": 0.0,
      "issue": 60010.0,
      "issueArea": 6.0,
      "decisionDirection": 1.0,
      "decisionDirectionDissent": 0.0,
      "authorityDecision1": 3.0,
      "authorityDecision2": 4.0,
      "lawType": 3.0,
      "lawSupp": 384.0,
      "lawMinor": NaN,
      "majOpinWriter": 94.0,
      "majOpinAssigner": 99.0,
      "splitVote": 1,
      "majVotes": 8,
      "minVotes": 0,
      "cite_id": "usrep434412",
      "outpath": "/Users/jnapolitano/Projects/supreme_court_transcripts/oyez/scdb_nodes/usrep434412.json"
}