{
      "caseId": "1992-088",
      "docketId": "1992-088-01",
      "caseIssuesId": "1992-088-01-01",
      "voteId": "1992-088-01-01-01",
      "dateDecision": "6/7/1993",
      "decisionType": 1,
      "usCite": "508 U.S. 429",
      "sctCite": "113 S. Ct. 2167",
      "ledCite": "124 L. Ed. 2d 391",
      "lexisCite": "1993 U.S. LEXIS 3870",
      "term": 1992,
      "naturalCourt": 1605,
      "chief": "Rehnquist",
      "docket": "91-7604",
      "caseName": "JEFFERY ANTOINE v. BYERS & ANDERSON, INC., et al.",
      "dateArgument": "3/30/1993",
      "dateRearg": NaN,
      "petitioner": 126.0,
      "petitionerState": NaN,
      "respondent": 216.0,
      "respondentState": NaN,
      "jurisdiction": 1.0,
      "adminAction": NaN,
      "adminActionState": NaN,
      "threeJudgeFdc": 0.0,
      "caseOrigin": 129.0,
      "caseOriginState": NaN,
      "caseSource": 29.0,
      "caseSourceState": NaN,
      "lcDisagreement": 0.0,
      "certReason": 2.0,
      "lcDisposition": 2.0,
      "lcDispositionDirection": 1.0,
      "declarationUncon": 1.0,
      "caseDisposition": 4.0,
      "caseDispositionUnusual": 0.0,
      "partyWinning": 1.0,
      "precedentAlteration": 0.0,
      "voteUnclear": 0.0,
      "issue": 80070.0,
      "issueArea": 8.0,
      "decisionDirection": 2.0,
      "decisionDirectionDissent": 0.0,
      "authorityDecision1": 3.0,
      "authorityDecision2": 7.0,
      "lawType": NaN,
      "lawSupp": NaN,
      "lawMinor": NaN,
      "majOpinWriter": 103.0,
      "majOpinAssigner": 102.0,
      "splitVote": 1,
      "majVotes": 9,
      "minVotes": 0,
      "cite_id": "usrep508429",
      "outpath": "/Users/jnapolitano/Projects/supreme_court_transcripts/oyez/scdb_nodes/usrep508429.json"
}