{"access_restricted": false, "aka": ["http://www.loc.gov/item/usrep190038/", "http://www.loc.gov/resource/usrep.usrep190038/", "http://www.loc.gov/item/usrep.usrep190038/"], "campaigns": [], "contributor": ["fuller, melville weston", "supreme court of the united states"], "date": "1902", "dates": ["1902-01-01T00:00:00Z"], "digitized": true, "extract_timestamp": "2021-06-29T13:37:19.035Z", "group": ["usrep102", "us-report"], "hassegments": false, "id": "http://www.loc.gov/item/usrep190038/", "image_url": ["https://tile.loc.gov/storage-services/service/ll/usrep/usrep190/usrep190038/usrep190038.gif#h=150&w=100"], "index": 4081, "item": {"call_number": ["Call Number: KF101", "Series: Civil Procedure", "Series: Volume 190"], "contributors": ["Fuller, Melville Weston (Judge)", "Supreme Court of the United States (Author)"], "created_published": ["1902"], "date": "19020000", "format": "periodical", "genre": ["Periodical"], "language": ["eng"], "notes": ["Description: U.S. Reports Volume 190; October Term, 1902; Tubman v. Baltimore and Ohio Railroad Company"], "rights": "no known restrictions on use or reproduction", "source_collection": "U.S. Reports", "subjects": ["Law", "Law Library", "Supreme Court", "United States", "Government Documents", "Judicial review and appeals", "Civil procedure", "Appellate courts", "Judicial powers", "U.S. Reports", "Common law", "Court opinions", "Judicial decisions", "Court cases", "Court decisions", "Motion to vacate", "Affirmation", "Periodical"], "title": "U.S. Reports: Tubman v. Baltimore & Ohio R. R., 190 U.S. 38 (1903)."}, "language": ["english"], "mime_type": ["image/gif", "application/pdf"], "online_format": ["image", "pdf"], "original_format": ["periodical"], "other_title": [], "partof": ["u.s. reports: civil procedure", "law library of congress", "united states reports (official opinions of the u.s. supreme court)", "u.s. reports: volume 190"], "resources": [{"files": 1, "image": "https://tile.loc.gov/storage-services/service/ll/usrep/usrep190/usrep190038/usrep190038.gif", "pdf": "https://tile.loc.gov/storage-services/service/ll/usrep/usrep190/usrep190038/usrep190038.pdf", "url": "https://www.loc.gov/resource/usrep.usrep190038/"}], "shelf_id": "Call Number: KF101 Series: Civil Procedure Series: Volume 190", "subject": ["motion to vacate", "common law", "judicial decisions", "judicial review and appeals", "court decisions", "supreme court", "appellate courts", "united states", "periodical", "government documents", "court opinions", "civil procedure", "judicial powers", "affirmation", "law library", "law", "u.s. reports", "court cases"], "subject_major_case_topic": ["civil procedure"], "timestamp": "2021-06-29T13:46:45.440Z", "title": "U.S. Reports: Tubman v. Baltimore & Ohio R. R., 190 U.S. 38 (1903).", "type": "legacyzoom", "url": "https://www.loc.gov/item/usrep190038/", "loc_id": "usrep190038"}