{"access_restricted": false, "aka": ["http://www.loc.gov/item/usrep216196/", "http://www.loc.gov/resource/usrep.usrep216196/", "http://www.loc.gov/item/usrep.usrep216196/"], "campaigns": [], "contributor": ["harlan, john marshall", "supreme court of the united states"], "date": "1909", "dates": ["1909-01-01T00:00:00Z"], "digitized": true, "extract_timestamp": "2021-06-29T13:37:22.264Z", "group": ["usrep102", "us-report"], "hassegments": false, "id": "http://www.loc.gov/item/usrep216196/", "image_url": ["https://tile.loc.gov/storage-services/service/ll/usrep/usrep216/usrep216196/usrep216196.gif#h=150&w=100"], "index": 10634, "item": {"call_number": ["Call Number: KF101", "Series: Contracts Law", "Series: Volume 216"], "contributors": ["Harlan, John Marshall (Judge)", "Supreme Court of the United States (Author)"], "created_published": ["1909"], "date": "19090000", "format": "periodical", "genre": ["Periodical"], "language": ["eng"], "notes": ["Description: U.S. Reports Volume 216; October Term, 1909; Citizens' Central National Bank of New York v. Appleton, Receiver of the Cooper Exchange Bank"], "rights": "no known restrictions on use or reproduction", "source_collection": "U.S. Reports", "subjects": ["Contracts", "Law", "Law Library", "Supreme Court", "United States", "Government Documents", "Judicial review and appeals", "Bankruptcy", "Banks and financial institutions", "Appellate courts", "Securities", "Financial services", "Corporations and associations", "Financial crises and stabilization", "U.S. Reports", "Common law", "Court opinions", "Judicial decisions", "Court cases", "Court decisions", "Periodical"], "title": "U.S. Reports: Citizens' National Bank v. Appleton, 216 U.S. 196 (1909)."}, "language": ["english"], "mime_type": ["image/gif", "application/pdf"], "online_format": ["image", "pdf"], "original_format": ["periodical"], "other_title": [], "partof": ["u.s. reports: volume 216", "law library of congress", "united states reports (official opinions of the u.s. supreme court)", "u.s. reports: contracts law"], "resources": [{"files": 1, "image": "https://tile.loc.gov/storage-services/service/ll/usrep/usrep216/usrep216196/usrep216196.gif", "pdf": "https://tile.loc.gov/storage-services/service/ll/usrep/usrep216/usrep216196/usrep216196.pdf", "url": "https://www.loc.gov/resource/usrep.usrep216196/"}], "shelf_id": "Call Number: KF101 Series: Contracts Law Series: Volume 216", "subject": ["supreme court", "united states", "court opinions", "periodical", "bankruptcy", "contracts law", "court cases", "judicial decisions", "banks and financial institutions", "law library", "u.s. reports", "judicial review and appeals", "contracts", "government documents", "law", "common law", "court decisions", "appellate courts", "securities", "corporations and associations", "financial services", "financial crises and stabilization"], "subject_major_case_topic": ["contracts law"], "timestamp": "2021-06-29T13:47:16.629Z", "title": "U.S. Reports: Citizens' National Bank v. Appleton, 216 U.S. 196 (1909).", "type": "legacyzoom", "url": "https://www.loc.gov/item/usrep216196/", "loc_id": "usrep216196"}