{"access_restricted": false, "aka": ["http://www.loc.gov/item/usrep522222/", "http://www.loc.gov/resource/usrep.usrep522222/", "http://www.loc.gov/item/usrep.usrep522222/"], "campaigns": [], "contributor": ["ginsburg, ruth bader", "supreme court of the united states"], "date": "1997", "dates": ["1997-01-01T00:00:00Z"], "digitized": true, "extract_timestamp": "2021-06-29T13:40:15.109Z", "group": ["usrep104", "us-report"], "hassegments": false, "id": "http://www.loc.gov/item/usrep522222/", "image_url": ["https://tile.loc.gov/storage-services/service/ll/usrep/usrep522/usrep522222/usrep522222.gif#h=150&w=100"], "index": 9781, "item": {"call_number": ["Call Number: KF101", "Series: Constitutional Law", "Series: Volume 522"], "contributors": ["Ginsburg, Ruth Bader (Judge)", "Supreme Court of the United States (Author)"], "created_published": ["1997"], "date": "19970000", "format": "periodical", "genre": ["Periodical"], "language": ["eng"], "notes": ["Description: U.S. Reports Volume 522; October Term, 1997; Kenneth Lee Baker and Steven Robert Baker, by his next friend, Melissa Thomas v. General Motors Corp."], "rights": "no known restrictions on use or reproduction", "source_collection": "U.S. Reports", "subjects": ["Law", "Witnesses", "Law Library", "Supreme Court", "United States", "Government Documents", "Judicial review and appeals", "Evidence", "State and local courts", "Civil actions", "Constitutional law", "U.S. Reports", "Common law", "Court opinions", "Judicial decisions", "Court cases", "Court decisions", "Full faith and credit", "Corporations", "Adjudication", "Michigan--United States", "Final judgment", "Subpoena power", "Limit on witness' testimony", "Periodical"], "title": "U.S. Reports: Baker v. General Motors Corp., 522 U.S. 222 (1998)."}, "language": ["english"], "mime_type": ["image/gif", "application/pdf"], "online_format": ["image", "pdf"], "original_format": ["periodical"], "other_title": [], "partof": ["u.s. reports: volume 522", "law library of congress", "united states reports (official opinions of the u.s. supreme court)", "u.s. reports: constitutional law"], "resources": [{"files": 1, "image": "https://tile.loc.gov/storage-services/service/ll/usrep/usrep522/usrep522222/usrep522222.gif", "pdf": "https://tile.loc.gov/storage-services/service/ll/usrep/usrep522/usrep522222/usrep522222.pdf", "url": "https://www.loc.gov/resource/usrep.usrep522222/"}], "shelf_id": "Call Number: KF101 Series: Constitutional Law Series: Volume 522", "subject": ["subpoena power", "supreme court", "adjudication", "united states", "court opinions", "periodical", "corporations", "law", "witnesses", "court cases", "judicial decisions", "law library", "judicial review and appeals", "state and local courts", "michigan", "limit on witness' testimony", "government documents", "evidence", "common law", "final judgment", "full faith and credit", "court decisions", "civil actions", "u.s. reports", "constitutional law"], "subject_major_case_topic": ["constitutional law"], "timestamp": "2021-06-29T13:55:42.607Z", "title": "U.S. Reports: Baker v. General Motors Corp., 522 U.S. 222 (1998).", "type": "legacyzoom", "url": "https://www.loc.gov/item/usrep522222/", "loc_id": "usrep522222"}