{"access_restricted": false, "aka": ["http://www.loc.gov/item/usrep085391/", "http://www.loc.gov/resource/usrep.usrep085391/", "http://www.loc.gov/item/usrep.usrep085391/"], "campaigns": [], "contributor": ["supreme court of the united states", "field, stephen johnson"], "date": "1873", "dates": ["1873-01-01T00:00:00Z"], "digitized": true, "extract_timestamp": "2021-06-29T13:35:56.354Z", "group": ["usrep101", "us-report"], "hassegments": false, "id": "http://www.loc.gov/item/usrep085391/", "image_url": ["https://tile.loc.gov/storage-services/service/ll/usrep/usrep085/usrep085391/usrep085391.gif#h=150&w=100"], "index": 7685, "item": {"call_number": ["Call Number: KF101", "Series: Conflicts of Law", "Series: Volume 85"], "contributors": ["Field, Stephen Johnson (Judge)", "Supreme Court of the United States (Author)"], "created_published": ["1873"], "date": "18730000", "format": "periodical", "genre": ["Periodical"], "language": ["eng"], "notes": ["Description: U.S. Reports Volume 85; Wallace Volume 18; October Term, 1873; Trask v. Maguire"], "rights": "no known restrictions on use or reproduction", "source_collection": "U.S. Reports", "subjects": ["Law", "Railroads", "Law Library", "Supreme Court", "United States", "Government Documents", "Judicial review and appeals", "Government property", "Securities", "State and local government", "State and local taxation", "Tax exemptions", "U.S. Reports", "Common law", "Court opinions", "Judicial decisions", "Court cases", "Court decisions", "Statutory construction", "Tax law", "St. Louis and Iron Mountain Railroad Company", "Periodical"], "title": "U.S. Reports: Trask v. Maguire, 85 U.S. (18 Wall.) 391 (1874)."}, "language": ["english"], "mime_type": ["image/gif", "application/pdf"], "online_format": ["image", "pdf"], "original_format": ["periodical"], "other_title": [], "partof": ["u.s. reports: volume 085", "law library of congress", "united states reports (official opinions of the u.s. supreme court)", "u.s. reports: conflicts of law"], "resources": [{"files": 1, "image": "https://tile.loc.gov/storage-services/service/ll/usrep/usrep085/usrep085391/usrep085391.gif", "pdf": "https://tile.loc.gov/storage-services/service/ll/usrep/usrep085/usrep085391/usrep085391.pdf", "url": "https://www.loc.gov/resource/usrep.usrep085391/"}], "shelf_id": "Call Number: KF101 Series: Conflicts of Law Series: Volume 85", "subject": ["government property", "railroads", "supreme court", "united states", "court opinions", "periodical", "state and local government", "tax law", "court cases", "judicial decisions", "statutory construction", "law library", "state and local taxation", "judicial review and appeals", "conflicts of law", "government documents", "law", "common law", "tax exemptions", "court decisions", "securities", "u.s. reports", "st. louis and iron mountain railroad company"], "subject_major_case_topic": ["conflicts of law"], "timestamp": "2021-06-29T13:43:08.305Z", "title": "U.S. Reports: Trask v. Maguire, 85 U.S. (18 Wall.) 391 (1874).", "type": "legacyzoom", "url": "https://www.loc.gov/item/usrep085391/", "loc_id": "usrep085391"}