{"access_restricted": false, "aka": ["http://www.loc.gov/item/usrep4641304/", "http://www.loc.gov/resource/usrep.usrep4641304/", "http://www.loc.gov/item/usrep.usrep4641304/"], "campaigns": [], "contributor": ["supreme court of the united states", "rehnquist, william h."], "date": "1983", "dates": ["1983-01-01T00:00:00Z"], "digitized": true, "extract_timestamp": "2021-06-29T13:40:09.868Z", "group": ["usrep104", "us-report"], "hassegments": false, "id": "http://www.loc.gov/item/usrep4641304/", "image_url": ["https://tile.loc.gov/storage-services/service/ll/usrep/usrep464/usrep4641304/usrep4641304.gif#h=150&w=100"], "index": 14464, "item": {"call_number": ["Call Number: KF101", "Series: Environmental Law", "Series: Volume 464"], "contributors": ["Rehnquist, William H. (Judge)", "Supreme Court of the United States (Author)"], "created_published": ["1983"], "date": "19830000", "format": "periodical", "genre": ["Periodical"], "language": ["eng"], "notes": ["Description: U.S. Reports Volume 464; October Term, 1983; Clark, Secretary of Interior, et al. v. California et al."], "rights": "no known restrictions on use or reproduction", "source_collection": "U.S. Reports", "subjects": ["Contracts", "Environment", "Law", "Law Library", "Supreme Court", "United States", "Government Documents", "Judicial review and appeals", "Public lands", "Public contracts and procurement", "Natural resources", "Energy", "Oil and gas", "Public utilities and utility rates", "U.S. Reports", "Common law", "Court opinions", "Judicial decisions", "Court cases", "Court decisions", "Coastal Zone Management Act of 1972", "Periodical"], "title": "U.S. Reports: Clark v. California, 464 U.S. 1304 (1983)."}, "language": ["english"], "mime_type": ["image/gif", "application/pdf"], "online_format": ["image", "pdf"], "original_format": ["periodical"], "other_title": [], "partof": ["u.s. reports: environmental law", "law library of congress", "united states reports (official opinions of the u.s. supreme court)", "u.s. reports: volume 464"], "resources": [{"files": 1, "image": "https://tile.loc.gov/storage-services/service/ll/usrep/usrep464/usrep4641304/usrep4641304.gif", "pdf": "https://tile.loc.gov/storage-services/service/ll/usrep/usrep464/usrep4641304/usrep4641304.pdf", "url": "https://www.loc.gov/resource/usrep.usrep4641304/"}], "shelf_id": "Call Number: KF101 Series: Environmental Law Series: Volume 464", "subject": ["oil and gas", "energy", "supreme court", "united states", "court opinions", "periodical", "public contracts and procurement", "environment", "coastal zone management act of 1972", "public utilities and utility rates", "court cases", "judicial decisions", "law library", "environmental law", "public lands", "judicial review and appeals", "contracts", "government documents", "law", "common law", "natural resources", "court decisions", "u.s. reports"], "subject_major_case_topic": ["environmental law"], "timestamp": "2021-06-29T13:54:57.068Z", "title": "U.S. Reports: Clark v. California, 464 U.S. 1304 (1983).", "type": "legacyzoom", "url": "https://www.loc.gov/item/usrep4641304/", "loc_id": "usrep4641304"}