{"access_restricted": false, "aka": ["http://www.loc.gov/item/usrep320222/", "http://www.loc.gov/resource/usrep.usrep320222/", "http://www.loc.gov/item/usrep.usrep320222/"], "campaigns": [], "contributor": ["supreme court of the united states"], "date": "1943", "dates": ["1943-01-01T00:00:00Z"], "digitized": true, "extract_timestamp": "2021-06-29T13:38:43.354Z", "group": ["usrep103", "us-report"], "hassegments": false, "id": "http://www.loc.gov/item/usrep320222/", "image_url": ["https://tile.loc.gov/storage-services/service/ll/usrep/usrep320/usrep320222/usrep320222.gif#h=150&w=100"], "index": 669, "item": {"call_number": ["Call Number: KF101", "Series: Administrative Law", "Series: Volume 320"], "contributors": ["Supreme Court of the United States (Author)"], "created_published": ["1943"], "date": "19430000", "format": "periodical", "genre": ["Periodical"], "language": ["eng"], "notes": ["Description: U.S. Reports Volume 320; October Term, 1943; Hunter Company, Inc. v. McHugh, Commissioner of Conservation, Et Al"], "rights": "no known restrictions on use or reproduction", "source_collection": "U.S. Reports", "subjects": ["Law", "Law Library", "Supreme Court", "United States", "Government Documents", "Judicial review and appeals", "Licensing and permits", "Jurisdiction and venue", "Natural resources", "Energy", "Oil and gas", "Administrative law and regulatory procedure", "U.S. Reports", "Common law", "Court opinions", "Judicial decisions", "Court cases", "Court decisions", "State and local laws", "Police powers", "Fourteenth Amendment", "Constitutional validity", "Gas drilling", "Periodical"], "title": "U.S. Reports: Hunter Co. v. McHugh, 320 U.S. 222 (1943)."}, "language": ["english"], "mime_type": ["image/gif", "application/pdf"], "online_format": ["image", "pdf"], "original_format": ["periodical"], "other_title": [], "partof": ["u.s. reports: administrative law", "law library of congress", "united states reports (official opinions of the u.s. supreme court)", "u.s. reports: volume 320"], "resources": [{"files": 1, "image": "https://tile.loc.gov/storage-services/service/ll/usrep/usrep320/usrep320222/usrep320222.gif", "pdf": "https://tile.loc.gov/storage-services/service/ll/usrep/usrep320/usrep320222/usrep320222.pdf", "url": "https://www.loc.gov/resource/usrep.usrep320222/"}], "shelf_id": "Call Number: KF101 Series: Administrative Law Series: Volume 320", "subject": ["administrative law", "oil and gas", "energy", "supreme court", "united states", "court opinions", "periodical", "jurisdiction and venue", "court cases", "judicial decisions", "law library", "judicial review and appeals", "police powers", "licensing and permits", "government documents", "administrative law and regulatory procedure", "law", "state and local laws", "common law", "natural resources", "court decisions", "fourteenth amendment", "u.s. reports", "gas drilling", "constitutional validity"], "subject_major_case_topic": ["administrative law"], "timestamp": "2021-06-29T13:50:49.345Z", "title": "U.S. Reports: Hunter Co. v. McHugh, 320 U.S. 222 (1943).", "type": "legacyzoom", "url": "https://www.loc.gov/item/usrep320222/", "loc_id": "usrep320222"}