{"access_restricted": false, "aka": ["http://www.loc.gov/item/usrep400455/", "http://www.loc.gov/resource/usrep.usrep400455/", "http://www.loc.gov/item/usrep.usrep400455/"], "campaigns": [], "contributor": ["supreme court of the united states", "douglas, william orville"], "date": "1970", "dates": ["1970-01-01T00:00:00Z"], "digitized": true, "extract_timestamp": "2021-06-29T13:38:57.394Z", "group": ["usrep103", "us-report"], "hassegments": false, "id": "http://www.loc.gov/item/usrep400455/", "image_url": ["https://tile.loc.gov/storage-services/service/ll/usrep/usrep400/usrep400455/usrep400455.gif#h=150&w=100"], "index": 12962, "item": {"call_number": ["Call Number: KF101", "Series: Criminal Law and Procedure", "Series: Volume 400"], "contributors": ["Douglas, William Orville (Judge)", "Supreme Court of the United States (Author)"], "created_published": ["1970"], "date": "19700000", "format": "periodical", "genre": ["Periodical"], "language": ["eng"], "notes": ["Description: U.S. Reports Volume 400; October Term, 1970; Mayberry v. Pennsylvania"], "rights": "no known restrictions on use or reproduction", "source_collection": "U.S. Reports", "subjects": ["Law", "Judges", "Legal history", "Law Library", "Supreme Court", "United States", "Government Documents", "Judicial review and appeals", "Civil procedure", "Correctional facilities and imprisonment", "Juries", "Due process", "Judicial powers", "U.S. Reports", "Common law", "Court opinions", "Judicial decisions", "Court cases", "Court decisions", "Contempt of court", "Legal ethics", "Pro se representation", "Legal training", "Court-appointed lawyer", "Periodical"], "title": "U.S. Reports: Mayberry v. Pennsylvania, 400 U.S. 455 (1971)."}, "language": ["english"], "mime_type": ["image/gif", "application/pdf"], "online_format": ["image", "pdf"], "original_format": ["periodical"], "other_title": [], "partof": ["u.s. reports: criminal law and procedure", "law library of congress", "united states reports (official opinions of the u.s. supreme court)", "u.s. reports: volume 400"], "resources": [{"files": 1, "image": "https://tile.loc.gov/storage-services/service/ll/usrep/usrep400/usrep400455/usrep400455.gif", "pdf": "https://tile.loc.gov/storage-services/service/ll/usrep/usrep400/usrep400455/usrep400455.pdf", "url": "https://www.loc.gov/resource/usrep.usrep400455/"}], "shelf_id": "Call Number: KF101 Series: Criminal Law and Procedure Series: Volume 400", "subject": ["periodical", "juries", "supreme court", "united states", "legal history", "court opinions", "judicial powers", "legal training", "judges", "due process", "court-appointed lawyer", "court cases", "judicial decisions", "law library", "legal ethics", "correctional facilities and imprisonment", "judicial review and appeals", "pro se representation", "government documents", "civil procedure", "contempt of court", "law", "common law", "court decisions", "u.s. reports", "criminal law and procedure"], "subject_major_case_topic": ["criminal law and procedure"], "timestamp": "2021-06-29T13:52:42.244Z", "title": "U.S. Reports: Mayberry v. Pennsylvania, 400 U.S. 455 (1971).", "type": "legacyzoom", "url": "https://www.loc.gov/item/usrep400455/", "loc_id": "usrep400455"}