{"access_restricted": false, "aka": ["http://www.loc.gov/item/usrep242238/", "http://www.loc.gov/resource/usrep.usrep242238/", "http://www.loc.gov/item/usrep.usrep242238/"], "campaigns": [], "contributor": ["supreme court of the united states", "pitney, mahlon"], "date": "1916", "dates": ["1916-01-01T00:00:00Z"], "digitized": true, "extract_timestamp": "2021-06-29T13:37:25.863Z", "group": ["usrep102", "us-report"], "hassegments": false, "id": "http://www.loc.gov/item/usrep242238/", "image_url": ["https://tile.loc.gov/storage-services/service/ll/usrep/usrep242/usrep242238/usrep242238.gif#h=150&w=100"], "index": 10728, "item": {"call_number": ["Call Number: KF101", "Series: Contracts Law", "Series: Volume 242"], "contributors": ["Pitney, Mahlon (Judge)", "Supreme Court of the United States (Author)"], "created_published": ["1916"], "date": "19160000", "format": "periodical", "genre": ["Periodical"], "language": ["eng"], "notes": ["Description: U.S. Reports Volume 242; October Term, 1916; Detroit United Railway v. People of the State of Michigan - Detroit United Railway v. City of Detroit"], "rights": "no known restrictions on use or reproduction", "source_collection": "U.S. Reports", "subjects": ["Contracts", "Law", "Railroads", "Legislators", "Law Library", "Supreme Court", "United States", "Government Documents", "Judicial review and appeals", "Jurisdiction and venue", "Civil procedure", "Boundaries", "Legislative powers", "Public contracts and procurement", "State and local courts", "State and local government", "Constitutional law", "Transportation and public works", "Public transit", "U.S. Reports", "Common law", "Court opinions", "Judicial decisions", "Court cases", "Court decisions", "Statutory construction", "Legislative history", "Transportation costs", "Contract Clause", "Periodical"], "title": "U.S. Reports: Detroit United Ry. v. Michigan, 242 U.S. 238 (1916)."}, "language": ["english"], "mime_type": ["image/gif", "application/pdf"], "online_format": ["image", "pdf"], "original_format": ["periodical"], "other_title": [], "partof": ["u.s. reports: volume 242", "law library of congress", "united states reports (official opinions of the u.s. supreme court)", "u.s. reports: contracts law"], "resources": [{"files": 1, "image": "https://tile.loc.gov/storage-services/service/ll/usrep/usrep242/usrep242238/usrep242238.gif", "pdf": "https://tile.loc.gov/storage-services/service/ll/usrep/usrep242/usrep242238/usrep242238.pdf", "url": "https://www.loc.gov/resource/usrep.usrep242238/"}], "shelf_id": "Call Number: KF101 Series: Contracts Law Series: Volume 242", "subject": ["legislative history", "jurisdiction and venue", "public transit", "railroads", "transportation and public works", "united states", "court opinions", "periodical", "contracts law", "contract clause", "public contracts and procurement", "state and local government", "boundaries", "court cases", "judicial decisions", "statutory construction", "law library", "legislators", "judicial review and appeals", "contracts", "state and local courts", "supreme court", "government documents", "civil procedure", "law", "transportation costs", "common law", "court decisions", "u.s. reports", "constitutional law", "legislative powers"], "subject_major_case_topic": ["contracts law"], "timestamp": "2021-06-29T13:47:48.616Z", "title": "U.S. Reports: Detroit United Ry. v. Michigan, 242 U.S. 238 (1916).", "type": "legacyzoom", "url": "https://www.loc.gov/item/usrep242238/", "loc_id": "usrep242238"}