{"access_restricted": false, "aka": ["http://www.loc.gov/item/usrep095242/", "http://www.loc.gov/resource/usrep.usrep095242/", "http://www.loc.gov/item/usrep.usrep095242/"], "campaigns": [], "contributor": ["supreme court of the united states", "clifford, nathan"], "date": "1877", "dates": ["1877-01-01T00:00:00Z"], "digitized": true, "extract_timestamp": "2021-06-29T13:35:58.341Z", "group": ["usrep101", "us-report"], "hassegments": false, "id": "http://www.loc.gov/item/usrep095242/", "image_url": ["https://tile.loc.gov/storage-services/service/ll/usrep/usrep095/usrep095242/usrep095242.gif#h=150&w=100"], "index": 16363, "item": {"call_number": ["Call Number: KF101", "Series: Insurance Law", "Series: Volume 95"], "contributors": ["Clifford, Nathan (Judge)", "Supreme Court of the United States (Author)"], "created_published": ["1877"], "date": "18770000", "format": "periodical", "genre": ["Periodical"], "language": ["eng"], "notes": ["Description: U.S. Reports Volume 95; October Term, 1877; Insurance Company v. Haven"], "rights": "no known restrictions on use or reproduction", "source_collection": "U.S. Reports", "subjects": ["Contracts", "Insurance", "Real Estate", "Law", "Law Library", "Supreme Court", "United States", "Government Documents", "Judicial review and appeals", "Property", "Ownership", "Buildings and property", "U.S. Reports", "Common law", "Court opinions", "Judicial decisions", "Court cases", "Court decisions", "Fire insurance", "Landlord and tenant", "Policy exclusions", "Periodical"], "title": "U.S. Reports: Insurance Co. v. Haven, 95 U.S. 242 (1877)."}, "language": ["english"], "mime_type": ["image/gif", "application/pdf"], "online_format": ["image", "pdf"], "original_format": ["periodical"], "other_title": [], "partof": ["u.s. reports: insurance law", "law library of congress", "united states reports (official opinions of the u.s. supreme court)", "u.s. reports: volume 095"], "resources": [{"files": 1, "image": "https://tile.loc.gov/storage-services/service/ll/usrep/usrep095/usrep095242/usrep095242.gif", "pdf": "https://tile.loc.gov/storage-services/service/ll/usrep/usrep095/usrep095242/usrep095242.pdf", "url": "https://www.loc.gov/resource/usrep.usrep095242/"}], "shelf_id": "Call Number: KF101 Series: Insurance Law Series: Volume 95", "subject": ["supreme court", "united states", "landlord and tenant", "periodical", "insurance", "court cases", "judicial decisions", "law library", "fire insurance", "judicial review and appeals", "contracts", "buildings and property", "government documents", "ownership", "law", "common law", "court decisions", "policy exclusions", "insurance law", "u.s. reports", "real estate", "court opinions", "property"], "subject_major_case_topic": ["insurance law"], "timestamp": "2021-06-29T13:43:25.609Z", "title": "U.S. Reports: Insurance Co. v. Haven, 95 U.S. 242 (1877).", "type": "legacyzoom", "url": "https://www.loc.gov/item/usrep095242/", "loc_id": "usrep095242"}