{"access_restricted": false, "aka": ["http://www.loc.gov/item/usrep457687/", "http://www.loc.gov/resource/usrep.usrep457687/", "http://www.loc.gov/item/usrep.usrep457687/"], "campaigns": [], "contributor": ["supreme court of the united states", "marshall, thurgood"], "date": "1981", "dates": ["1981-01-01T00:00:00Z"], "digitized": true, "extract_timestamp": "2021-06-29T13:40:09.205Z", "group": ["usrep104", "us-report"], "hassegments": false, "id": "http://www.loc.gov/item/usrep457687/", "image_url": ["https://tile.loc.gov/storage-services/service/ll/usrep/usrep457/usrep457687/usrep457687.gif#h=150&w=100"], "index": 15201, "item": {"call_number": ["Call Number: KF101", "Series: Evidence", "Series: Volume 457"], "contributors": ["Marshall, Thurgood (Judge)", "Supreme Court of the United States (Author)"], "created_published": ["1981"], "date": "19810000", "format": "periodical", "genre": ["Periodical"], "language": ["eng"], "notes": ["Description: U.S. Reports Volume 457; October Term, 1981; Taylor v. Alabama"], "rights": "no known restrictions on use or reproduction", "source_collection": "U.S. Reports", "subjects": ["Law", "Testimony", "Law Library", "Supreme Court", "United States", "Government Documents", "Judicial review and appeals", "Evidence", "law enforcement officers", "Correctional facilities and imprisonment", "Criminal law and procedure", "Constitutional law", "Human rights and civil liberties", "Crime and law enforcement", "Robbery", "Warrant", "U.S. Reports", "Common law", "Court opinions", "Judicial decisions", "Court cases", "Court decisions", "Probable cause", "Miranda rights", "Miranda v. Arizona", "Interrogation", "Confession", "Illegal arrest", "Periodical"], "title": "U.S. Reports: Taylor v. Alabama, 457 U.S. 687 (1982)."}, "language": ["english"], "mime_type": ["image/gif", "application/pdf"], "online_format": ["image", "pdf"], "original_format": ["periodical"], "other_title": [], "partof": ["u.s. reports: evidence", "law library of congress", "united states reports (official opinions of the u.s. supreme court)", "u.s. reports: volume 457"], "resources": [{"files": 1, "image": "https://tile.loc.gov/storage-services/service/ll/usrep/usrep457/usrep457687/usrep457687.gif", "pdf": "https://tile.loc.gov/storage-services/service/ll/usrep/usrep457/usrep457687/usrep457687.pdf", "url": "https://www.loc.gov/resource/usrep.usrep457687/"}], "shelf_id": "Call Number: KF101 Series: Evidence Series: Volume 457", "subject": ["law enforcement officers", "confession", "supreme court", "evidence", "united states", "court opinions", "periodical", "probable cause", "miranda rights", "common law", "human rights and civil liberties", "court cases", "judicial decisions", "law library", "warrant", "correctional facilities and imprisonment", "judicial review and appeals", "illegal arrest", "interrogation", "government documents", "law", "criminal law and procedure", "crime and law enforcement", "court decisions", "miranda v. arizona", "u.s. reports", "constitutional law", "robbery", "testimony"], "subject_major_case_topic": ["evidence"], "timestamp": "2021-06-29T13:54:51.404Z", "title": "U.S. Reports: Taylor v. Alabama, 457 U.S. 687 (1982).", "type": "legacyzoom", "url": "https://www.loc.gov/item/usrep457687/", "loc_id": "usrep457687"}