{"access_restricted": false, "aka": ["http://www.loc.gov/item/usrep379650/", "http://www.loc.gov/resource/usrep.usrep379650/", "http://www.loc.gov/item/usrep.usrep379650/"], "campaigns": [], "contributor": ["supreme court of the united states", "harlan ii, john marshall"], "date": "1964", "dates": ["1964-01-01T00:00:00Z"], "digitized": true, "extract_timestamp": "2021-06-29T13:38:52.785Z", "group": ["usrep103", "us-report"], "hassegments": false, "id": "http://www.loc.gov/item/usrep379650/", "image_url": ["https://tile.loc.gov/storage-services/service/ll/usrep/usrep379/usrep379650/usrep379650.gif#h=150&w=100"], "index": 18227, "item": {"call_number": ["Call Number: KF101", "Series: Labor and Employment Law", "Series: Volume 379"], "contributors": ["Harlan II, John Marshall (Judge)", "Supreme Court of the United States (Author)"], "created_published": ["1964"], "date": "19640000", "format": "periodical", "genre": ["Periodical"], "language": ["eng"], "notes": ["Description: U.S. Reports Volume 379; October Term, 1964; Republic Steel Corp. v. Maddox"], "rights": "no known restrictions on use or reproduction", "source_collection": "U.S. Reports", "subjects": ["Law", "Law Library", "Supreme Court", "United States", "Government Documents", "Judicial review and appeals", "Employee benefits", "Labor-management relations", "Collective bargaining", "U.S. Reports", "Common law", "Court opinions", "Judicial decisions", "Court cases", "Court decisions", "Labor and employment law", "Union", "Severance pay", "Grievance procedures", "Contract grievances", "Federal labor law", "Periodical"], "title": "U.S. Reports: Republic Steel v. Maddox, 379 U.S. 650 (1965)."}, "language": ["english"], "mime_type": ["image/gif", "application/pdf"], "online_format": ["image", "pdf"], "original_format": ["periodical"], "other_title": [], "partof": ["u.s. reports: volume 379", "u.s. reports: labor and employment law", "law library of congress", "united states reports (official opinions of the u.s. supreme court)"], "resources": [{"files": 1, "image": "https://tile.loc.gov/storage-services/service/ll/usrep/usrep379/usrep379650/usrep379650.gif", "pdf": "https://tile.loc.gov/storage-services/service/ll/usrep/usrep379/usrep379650/usrep379650.pdf", "url": "https://www.loc.gov/resource/usrep.usrep379650/"}], "shelf_id": "Call Number: KF101 Series: Labor and Employment Law Series: Volume 379", "subject": ["federal labor law", "supreme court", "united states", "court opinions", "periodical", "union", "labor and employment law", "grievance procedures", "labor-management relations", "collective bargaining", "court cases", "judicial decisions", "law library", "judicial review and appeals", "employee benefits", "government documents", "severance pay", "law", "common law", "court decisions", "contract grievances", "u.s. reports"], "subject_major_case_topic": ["labor and employment law"], "timestamp": "2021-06-29T13:52:05.473Z", "title": "U.S. Reports: Republic Steel v. Maddox, 379 U.S. 650 (1965).", "type": "legacyzoom", "url": "https://www.loc.gov/item/usrep379650/", "loc_id": "usrep379650"}