{"access_restricted": false, "aka": ["http://www.loc.gov/item/usrep296207/", "http://www.loc.gov/resource/usrep.usrep296207/", "http://www.loc.gov/item/usrep.usrep296207/"], "campaigns": [], "contributor": ["supreme court of the united states", "sutherland, george"], "date": "1935", "dates": ["1935-01-01T00:00:00Z"], "digitized": true, "extract_timestamp": "2021-06-29T13:38:39.665Z", "group": ["usrep103", "us-report"], "hassegments": false, "id": "http://www.loc.gov/item/usrep296207/", "image_url": ["https://tile.loc.gov/storage-services/service/ll/usrep/usrep296/usrep296207/usrep296207.gif#h=150&w=100"], "index": 4892, "item": {"call_number": ["Call Number: KF101", "Series: Civil Procedure", "Series: Volume 296"], "contributors": ["Sutherland, George (Judge)", "Supreme Court of the United States (Author)"], "created_published": ["1935"], "date": "19350000", "format": "periodical", "genre": ["Periodical"], "language": ["eng"], "notes": ["Description: U.S. Reports Volume 296; October Term, 1935; Fox Film Corp. v. Muller"], "rights": "no known restrictions on use or reproduction", "source_collection": "U.S. Reports", "subjects": ["Contracts", "Law", "Law Library", "Supreme Court", "United States", "Government Documents", "Judicial review and appeals", "Licensing and permits", "Jurisdiction and venue", "Competition and antitrust", "U.S. Reports", "Common law", "Court opinions", "Judicial decisions", "Court cases", "Court decisions", "Arbitration Clause", "Severable provisions", "Independent Federal question", "Enterprise Irrigation District v. Canal Co.", "Periodical"], "title": "U.S. Reports: Fox Film Corp. v. Muller, 296 U.S. 207 (1935)."}, "language": ["english"], "mime_type": ["image/gif", "application/pdf"], "online_format": ["image", "pdf"], "original_format": ["periodical"], "other_title": [], "partof": ["u.s. reports: volume 296", "u.s. reports: civil procedure", "law library of congress", "united states reports (official opinions of the u.s. supreme court)"], "resources": [{"files": 1, "image": "https://tile.loc.gov/storage-services/service/ll/usrep/usrep296/usrep296207/usrep296207.gif", "pdf": "https://tile.loc.gov/storage-services/service/ll/usrep/usrep296/usrep296207/usrep296207.pdf", "url": "https://www.loc.gov/resource/usrep.usrep296207/"}], "shelf_id": "Call Number: KF101 Series: Civil Procedure Series: Volume 296", "subject": ["competition and antitrust", "jurisdiction and venue", "supreme court", "united states", "court opinions", "periodical", "court cases", "judicial decisions", "law library", "independent federal question", "arbitration clause", "enterprise irrigation district v. canal co.", "judicial review and appeals", "contracts", "severable provisions", "licensing and permits", "government documents", "civil procedure", "law", "common law", "court decisions", "u.s. reports"], "subject_major_case_topic": ["civil procedure"], "timestamp": "2021-06-29T13:50:18.834Z", "title": "U.S. Reports: Fox Film Corp. v. Muller, 296 U.S. 207 (1935).", "type": "legacyzoom", "url": "https://www.loc.gov/item/usrep296207/", "loc_id": "usrep296207"}